odoo/addons/ssi_hr_reimbursement/README.rst
odoo/addons/ssi_hr_reimbursement/__init__.py
odoo/addons/ssi_hr_reimbursement/__manifest__.py
odoo/addons/ssi_hr_reimbursement/data/account_journal_data.xml
odoo/addons/ssi_hr_reimbursement/data/approval_template_data.xml
odoo/addons/ssi_hr_reimbursement/data/base_automation_data.xml
odoo/addons/ssi_hr_reimbursement/data/ir_actions_server_data.xml
odoo/addons/ssi_hr_reimbursement/data/ir_sequence_data.xml
odoo/addons/ssi_hr_reimbursement/data/policy_template_data.xml
odoo/addons/ssi_hr_reimbursement/data/sequence_template_data.xml
odoo/addons/ssi_hr_reimbursement/demo/account_account_demo.xml
odoo/addons/ssi_hr_reimbursement/demo/account_journal_demo.xml
odoo/addons/ssi_hr_reimbursement/demo/hr_expense_type_demo.xml
odoo/addons/ssi_hr_reimbursement/i18n/ssi_hr_reimbursement.pot
odoo/addons/ssi_hr_reimbursement/models/__init__.py
odoo/addons/ssi_hr_reimbursement/models/account_move.py
odoo/addons/ssi_hr_reimbursement/models/hr_expense_type.py
odoo/addons/ssi_hr_reimbursement/models/hr_reimbursement.py
odoo/addons/ssi_hr_reimbursement/models/hr_reimbursement_line.py
odoo/addons/ssi_hr_reimbursement/security/ir.model.access.csv
odoo/addons/ssi_hr_reimbursement/security/ir_module_category_data.xml
odoo/addons/ssi_hr_reimbursement/security/ir_rule_data.xml
odoo/addons/ssi_hr_reimbursement/security/res_group_data.xml
odoo/addons/ssi_hr_reimbursement/static/description/icon.png
odoo/addons/ssi_hr_reimbursement/static/description/icon_timesheet.png
odoo/addons/ssi_hr_reimbursement/views/hr_expense_type_views.xml
odoo/addons/ssi_hr_reimbursement/views/hr_reimbursement_views.xml
odoo14_addon_ssi_hr_reimbursement-14.0.3.1.0.dist-info/METADATA
odoo14_addon_ssi_hr_reimbursement-14.0.3.1.0.dist-info/WHEEL
odoo14_addon_ssi_hr_reimbursement-14.0.3.1.0.dist-info/top_level.txt
odoo14_addon_ssi_hr_reimbursement-14.0.3.1.0.dist-info/RECORD
